{
	"name": "pl_dwh_Dimensiones_3",
	"properties": {
		"description": "Carga Información Dimensiones",
		"activities": [
			{
				"name": "dim_CargaTipoDocumentoTarjeta",
				"type": "SqlServerStoredProcedure",
				"dependsOn": [],
				"policy": {
					"timeout": "7.00:00:00",
					"retry": 0,
					"retryIntervalInSeconds": 30,
					"secureOutput": false,
					"secureInput": false
				},
				"userProperties": [],
				"typeProperties": {
					"storedProcedureName": "[admin_btc].[usp_EjecutaSP]",
					"storedProcedureParameters": {
						"Esquema": {
							"value": "dwh_dim",
							"type": "String"
						},
						"IDCadenaSistemaGerente": {
							"value": {
								"value": "@pipeline().parameters.IDCadenaSistemaGerente",
								"type": "Expression"
							},
							"type": "Int32"
						},
						"Pais": {
							"value": {
								"value": "@pipeline().parameters.Pais",
								"type": "Expression"
							},
							"type": "String"
						},
						"Procedimiento": {
							"value": "usp_CargaTipoDocumentoTarjeta",
							"type": "String"
						},
						"TipoCarga": {
							"value": {
								"value": "@pipeline().parameters.TipoCarga",
								"type": "Expression"
							},
							"type": "String"
						}
					}
				},
				"linkedServiceName": {
					"referenceName": "linked_dwh",
					"type": "LinkedServiceReference"
				}
			},
			{
				"name": "dim_CargaClaseTarjeta",
				"type": "SqlServerStoredProcedure",
				"dependsOn": [],
				"policy": {
					"timeout": "7.00:00:00",
					"retry": 0,
					"retryIntervalInSeconds": 30,
					"secureOutput": false,
					"secureInput": false
				},
				"userProperties": [],
				"typeProperties": {
					"storedProcedureName": "[admin_btc].[usp_EjecutaSP]",
					"storedProcedureParameters": {
						"Esquema": {
							"value": "dwh_dim",
							"type": "String"
						},
						"IDCadenaSistemaGerente": {
							"value": {
								"value": "@pipeline().parameters.IDCadenaSistemaGerente",
								"type": "Expression"
							},
							"type": "Int32"
						},
						"Pais": {
							"value": {
								"value": "@pipeline().parameters.Pais",
								"type": "Expression"
							},
							"type": "String"
						},
						"Procedimiento": {
							"value": "usp_CargaClaseTarjeta",
							"type": "String"
						},
						"TipoCarga": {
							"value": {
								"value": "@pipeline().parameters.TipoCarga",
								"type": "Expression"
							},
							"type": "String"
						}
					}
				},
				"linkedServiceName": {
					"referenceName": "linked_dwh",
					"type": "LinkedServiceReference"
				}
			},
			{
				"name": "dim_CargaAdquirente",
				"type": "SqlServerStoredProcedure",
				"dependsOn": [],
				"policy": {
					"timeout": "7.00:00:00",
					"retry": 0,
					"retryIntervalInSeconds": 30,
					"secureOutput": false,
					"secureInput": false
				},
				"userProperties": [],
				"typeProperties": {
					"storedProcedureName": "[admin_btc].[usp_EjecutaSP]",
					"storedProcedureParameters": {
						"Esquema": {
							"value": "dwh_dim",
							"type": "String"
						},
						"IDCadenaSistemaGerente": {
							"value": {
								"value": "@pipeline().parameters.IDCadenaSistemaGerente",
								"type": "Expression"
							},
							"type": "Int32"
						},
						"Pais": {
							"value": {
								"value": "@pipeline().parameters.Pais",
								"type": "Expression"
							},
							"type": "String"
						},
						"Procedimiento": {
							"value": "usp_CargaAdquirente",
							"type": "String"
						},
						"TipoCarga": {
							"value": {
								"value": "@pipeline().parameters.TipoCarga",
								"type": "Expression"
							},
							"type": "String"
						}
					}
				},
				"linkedServiceName": {
					"referenceName": "linked_dwh",
					"type": "LinkedServiceReference"
				}
			},
			{
				"name": "dim_CargaDenominacionProyecto",
				"type": "SqlServerStoredProcedure",
				"dependsOn": [],
				"policy": {
					"timeout": "7.00:00:00",
					"retry": 0,
					"retryIntervalInSeconds": 30,
					"secureOutput": false,
					"secureInput": false
				},
				"userProperties": [],
				"typeProperties": {
					"storedProcedureName": "[admin_btc].[usp_EjecutaSP]",
					"storedProcedureParameters": {
						"Esquema": {
							"value": "dwh_dim",
							"type": "String"
						},
						"IDCadenaSistemaGerente": {
							"value": {
								"value": "@pipeline().parameters.IDCadenaSistemaGerente",
								"type": "Expression"
							},
							"type": "Int32"
						},
						"Pais": {
							"value": {
								"value": "@pipeline().parameters.Pais",
								"type": "Expression"
							},
							"type": "String"
						},
						"Procedimiento": {
							"value": "usp_CargaDenominacionProyecto",
							"type": "String"
						},
						"TipoCarga": {
							"value": {
								"value": "@pipeline().parameters.TipoCarga",
								"type": "Expression"
							},
							"type": "String"
						}
					}
				},
				"linkedServiceName": {
					"referenceName": "linked_dwh",
					"type": "LinkedServiceReference"
				}
			},
			{
				"name": "dim_CargaCentroCostoConstruciones",
				"type": "SqlServerStoredProcedure",
				"dependsOn": [],
				"policy": {
					"timeout": "7.00:00:00",
					"retry": 0,
					"retryIntervalInSeconds": 30,
					"secureOutput": false,
					"secureInput": false
				},
				"userProperties": [],
				"typeProperties": {
					"storedProcedureName": "[admin_btc].[usp_EjecutaSP]",
					"storedProcedureParameters": {
						"Esquema": {
							"value": "dwh_dim",
							"type": "String"
						},
						"IDCadenaSistemaGerente": {
							"value": {
								"value": "@pipeline().parameters.IDCadenaSistemaGerente",
								"type": "Expression"
							},
							"type": "Int32"
						},
						"Pais": {
							"value": {
								"value": "@pipeline().parameters.Pais",
								"type": "Expression"
							},
							"type": "String"
						},
						"Procedimiento": {
							"value": "usp_CargaCentroCostoConstruciones",
							"type": "String"
						},
						"TipoCarga": {
							"value": {
								"value": "@pipeline().parameters.TipoCarga",
								"type": "Expression"
							},
							"type": "String"
						}
					}
				},
				"linkedServiceName": {
					"referenceName": "linked_dwh",
					"type": "LinkedServiceReference"
				}
			},
			{
				"name": "dim_CargaCadenaConstruciones",
				"type": "SqlServerStoredProcedure",
				"dependsOn": [],
				"policy": {
					"timeout": "7.00:00:00",
					"retry": 0,
					"retryIntervalInSeconds": 30,
					"secureOutput": false,
					"secureInput": false
				},
				"userProperties": [],
				"typeProperties": {
					"storedProcedureName": "[admin_btc].[usp_EjecutaSP]",
					"storedProcedureParameters": {
						"Esquema": {
							"value": "dwh_dim",
							"type": "String"
						},
						"IDCadenaSistemaGerente": {
							"value": {
								"value": "@pipeline().parameters.IDCadenaSistemaGerente",
								"type": "Expression"
							},
							"type": "Int32"
						},
						"Pais": {
							"value": {
								"value": "@pipeline().parameters.Pais",
								"type": "Expression"
							},
							"type": "String"
						},
						"Procedimiento": {
							"value": "usp_CargaCadenaConstruccion",
							"type": "String"
						},
						"TipoCarga": {
							"value": {
								"value": "@pipeline().parameters.TipoCarga",
								"type": "Expression"
							},
							"type": "String"
						}
					}
				},
				"linkedServiceName": {
					"referenceName": "linked_dwh",
					"type": "LinkedServiceReference"
				}
			},
			{
				"name": "dim_PuntoExpedicion",
				"type": "SqlServerStoredProcedure",
				"dependsOn": [],
				"policy": {
					"timeout": "7.00:00:00",
					"retry": 0,
					"retryIntervalInSeconds": 30,
					"secureOutput": false,
					"secureInput": false
				},
				"userProperties": [],
				"typeProperties": {
					"storedProcedureName": "[admin_btc].[usp_EjecutaSP]",
					"storedProcedureParameters": {
						"Esquema": {
							"value": "dwh_dim",
							"type": "String"
						},
						"IDCadenaSistemaGerente": {
							"value": {
								"value": "@pipeline().parameters.IDCadenaSistemaGerente",
								"type": "Expression"
							},
							"type": "Int32"
						},
						"Pais": {
							"value": {
								"value": "@pipeline().parameters.Pais",
								"type": "Expression"
							},
							"type": "String"
						},
						"Procedimiento": {
							"value": "usp_CargaPuntoExpedicion",
							"type": "String"
						},
						"TipoCarga": {
							"value": {
								"value": "@pipeline().parameters.TipoCarga",
								"type": "Expression"
							},
							"type": "String"
						}
					}
				},
				"linkedServiceName": {
					"referenceName": "linked_dwh",
					"type": "LinkedServiceReference"
				}
			},
			{
				"name": "dim_ClientePos",
				"type": "SqlServerStoredProcedure",
				"dependsOn": [],
				"policy": {
					"timeout": "7.00:00:00",
					"retry": 0,
					"retryIntervalInSeconds": 30,
					"secureOutput": false,
					"secureInput": false
				},
				"userProperties": [],
				"typeProperties": {
					"storedProcedureName": "[admin_btc].[usp_EjecutaSP]",
					"storedProcedureParameters": {
						"Esquema": {
							"value": "dwh_dim",
							"type": "String"
						},
						"IDCadenaSistemaGerente": {
							"value": {
								"value": "@pipeline().parameters.IDCadenaSistemaGerente",
								"type": "Expression"
							},
							"type": "Int32"
						},
						"Pais": {
							"value": {
								"value": "@pipeline().parameters.Pais",
								"type": "Expression"
							},
							"type": "String"
						},
						"Procedimiento": {
							"value": "usp_CargaClientePos",
							"type": "String"
						},
						"TipoCarga": {
							"value": {
								"value": "@pipeline().parameters.TipoCarga",
								"type": "Expression"
							},
							"type": "String"
						}
					}
				},
				"linkedServiceName": {
					"referenceName": "linked_dwh",
					"type": "LinkedServiceReference"
				}
			},
			{
				"name": "dim_Persona",
				"type": "SqlServerStoredProcedure",
				"dependsOn": [],
				"policy": {
					"timeout": "7.00:00:00",
					"retry": 0,
					"retryIntervalInSeconds": 30,
					"secureOutput": false,
					"secureInput": false
				},
				"userProperties": [],
				"typeProperties": {
					"storedProcedureName": "[admin_btc].[usp_EjecutaSP]",
					"storedProcedureParameters": {
						"Esquema": {
							"value": "dwh_dim",
							"type": "String"
						},
						"IDCadenaSistemaGerente": {
							"value": {
								"value": "@pipeline().parameters.IDCadenaSistemaGerente",
								"type": "Expression"
							},
							"type": "Int32"
						},
						"Pais": {
							"value": {
								"value": "@pipeline().parameters.Pais",
								"type": "Expression"
							},
							"type": "String"
						},
						"Procedimiento": {
							"value": "usp_CargaPersona",
							"type": "String"
						},
						"TipoCarga": {
							"value": {
								"value": "@pipeline().parameters.TipoCarga",
								"type": "Expression"
							},
							"type": "String"
						}
					}
				},
				"linkedServiceName": {
					"referenceName": "linked_dwh",
					"type": "LinkedServiceReference"
				}
			},
			{
				"name": "dim_UsuarioPos",
				"type": "SqlServerStoredProcedure",
				"dependsOn": [],
				"policy": {
					"timeout": "7.00:00:00",
					"retry": 0,
					"retryIntervalInSeconds": 30,
					"secureOutput": false,
					"secureInput": false
				},
				"userProperties": [],
				"typeProperties": {
					"storedProcedureName": "[admin_btc].[usp_EjecutaSP]",
					"storedProcedureParameters": {
						"Esquema": {
							"value": "dwh_dim",
							"type": "String"
						},
						"IDCadenaSistemaGerente": {
							"value": {
								"value": "@pipeline().parameters.IDCadenaSistemaGerente",
								"type": "Expression"
							},
							"type": "Int32"
						},
						"Pais": {
							"value": {
								"value": "@pipeline().parameters.Pais",
								"type": "Expression"
							},
							"type": "String"
						},
						"Procedimiento": {
							"value": "usp_CargaUsuarioPos",
							"type": "String"
						},
						"TipoCarga": {
							"value": {
								"value": "@pipeline().parameters.TipoCarga",
								"type": "Expression"
							},
							"type": "String"
						}
					}
				},
				"linkedServiceName": {
					"referenceName": "linked_dwh",
					"type": "LinkedServiceReference"
				}
			},
			{
				"name": "dim_AreaCentroBeneficio",
				"type": "SqlServerStoredProcedure",
				"dependsOn": [],
				"policy": {
					"timeout": "7.00:00:00",
					"retry": 0,
					"retryIntervalInSeconds": 30,
					"secureOutput": false,
					"secureInput": false
				},
				"userProperties": [],
				"typeProperties": {
					"storedProcedureName": "[admin_btc].[usp_EjecutaSP]",
					"storedProcedureParameters": {
						"Esquema": {
							"value": "dwh_dim",
							"type": "String"
						},
						"IDCadenaSistemaGerente": {
							"value": {
								"value": "@pipeline().parameters.IDCadenaSistemaGerente",
								"type": "Expression"
							},
							"type": "Int32"
						},
						"Pais": {
							"value": {
								"value": "@pipeline().parameters.Pais",
								"type": "Expression"
							},
							"type": "String"
						},
						"Procedimiento": {
							"value": "usp_CargaAreaCentroBeneficio",
							"type": "String"
						},
						"TipoCarga": {
							"value": {
								"value": "@pipeline().parameters.TipoCarga",
								"type": "Expression"
							},
							"type": "String"
						}
					}
				},
				"linkedServiceName": {
					"referenceName": "linked_dwh",
					"type": "LinkedServiceReference"
				}
			},
			{
				"name": "dim_CategoriaValoracion",
				"type": "SqlServerStoredProcedure",
				"dependsOn": [],
				"policy": {
					"timeout": "7.00:00:00",
					"retry": 0,
					"retryIntervalInSeconds": 30,
					"secureOutput": false,
					"secureInput": false
				},
				"userProperties": [],
				"typeProperties": {
					"storedProcedureName": "[admin_btc].[usp_EjecutaSP]",
					"storedProcedureParameters": {
						"Esquema": {
							"value": "dwh_dim",
							"type": "String"
						},
						"IDCadenaSistemaGerente": {
							"value": {
								"value": "@pipeline().parameters.IDCadenaSistemaGerente",
								"type": "Expression"
							},
							"type": "Int32"
						},
						"Pais": {
							"value": {
								"value": "@pipeline().parameters.Pais",
								"type": "Expression"
							},
							"type": "String"
						},
						"Procedimiento": {
							"value": "usp_CargaCategoriaValoracion",
							"type": "String"
						},
						"TipoCarga": {
							"value": {
								"value": "@pipeline().parameters.TipoCarga",
								"type": "Expression"
							},
							"type": "String"
						}
					}
				},
				"linkedServiceName": {
					"referenceName": "linked_dwh",
					"type": "LinkedServiceReference"
				}
			},
			{
				"name": "dim_Planta",
				"type": "SqlServerStoredProcedure",
				"dependsOn": [],
				"policy": {
					"timeout": "7.00:00:00",
					"retry": 0,
					"retryIntervalInSeconds": 30,
					"secureOutput": false,
					"secureInput": false
				},
				"userProperties": [],
				"typeProperties": {
					"storedProcedureName": "[admin_btc].[usp_EjecutaSP]",
					"storedProcedureParameters": {
						"Esquema": {
							"value": "dwh_dim",
							"type": "String"
						},
						"IDCadenaSistemaGerente": {
							"value": {
								"value": "@pipeline().parameters.IDCadenaSistemaGerente",
								"type": "Expression"
							},
							"type": "Int32"
						},
						"Pais": {
							"value": {
								"value": "@pipeline().parameters.Pais",
								"type": "Expression"
							},
							"type": "String"
						},
						"Procedimiento": {
							"value": "usp_CargaPlanta",
							"type": "String"
						},
						"TipoCarga": {
							"value": {
								"value": "@pipeline().parameters.TipoCarga",
								"type": "Expression"
							},
							"type": "String"
						}
					}
				},
				"linkedServiceName": {
					"referenceName": "linked_dwh",
					"type": "LinkedServiceReference"
				}
			},
			{
				"name": "dim_TipoCondicion",
				"type": "SqlServerStoredProcedure",
				"dependsOn": [],
				"policy": {
					"timeout": "7.00:00:00",
					"retry": 0,
					"retryIntervalInSeconds": 30,
					"secureOutput": false,
					"secureInput": false
				},
				"userProperties": [],
				"typeProperties": {
					"storedProcedureName": "[admin_btc].[usp_EjecutaSP]",
					"storedProcedureParameters": {
						"Esquema": {
							"value": "dwh_dim",
							"type": "String"
						},
						"IDCadenaSistemaGerente": {
							"value": {
								"value": "@pipeline().parameters.IDCadenaSistemaGerente",
								"type": "Expression"
							},
							"type": "Int32"
						},
						"Pais": {
							"value": {
								"value": "@pipeline().parameters.Pais",
								"type": "Expression"
							},
							"type": "String"
						},
						"Procedimiento": {
							"value": "usp_CargaTipoCondicion",
							"type": "String"
						},
						"TipoCarga": {
							"value": {
								"value": "@pipeline().parameters.TipoCarga",
								"type": "Expression"
							},
							"type": "String"
						}
					}
				},
				"linkedServiceName": {
					"referenceName": "linked_dwh",
					"type": "LinkedServiceReference"
				}
			},
			{
				"name": "dim_TipoDocumento",
				"type": "SqlServerStoredProcedure",
				"dependsOn": [],
				"policy": {
					"timeout": "7.00:00:00",
					"retry": 0,
					"retryIntervalInSeconds": 30,
					"secureOutput": false,
					"secureInput": false
				},
				"userProperties": [],
				"typeProperties": {
					"storedProcedureName": "[admin_btc].[usp_EjecutaSP]",
					"storedProcedureParameters": {
						"Esquema": {
							"value": "dwh_dim",
							"type": "String"
						},
						"IDCadenaSistemaGerente": {
							"value": {
								"value": "@pipeline().parameters.IDCadenaSistemaGerente",
								"type": "Expression"
							},
							"type": "Int32"
						},
						"Pais": {
							"value": {
								"value": "@pipeline().parameters.Pais",
								"type": "Expression"
							},
							"type": "String"
						},
						"Procedimiento": {
							"value": "usp_CargaTipDocumento",
							"type": "String"
						},
						"TipoCarga": {
							"value": {
								"value": "@pipeline().parameters.TipoCarga",
								"type": "Expression"
							},
							"type": "String"
						}
					}
				},
				"linkedServiceName": {
					"referenceName": "linked_dwh",
					"type": "LinkedServiceReference"
				}
			}
		],
		"parameters": {
			"IDCadenaSistemaGerente": {
				"type": "int",
				"defaultValue": 0
			},
			"Pais": {
				"type": "String",
				"defaultValue": "ECU"
			},
			"TipoCarga": {
				"type": "String",
				"defaultValue": "MANUAL"
			}
		},
		"folder": {
			"name": "dwh_Dimensiones"
		},
		"annotations": []
	},
	"type": "Microsoft.DataFactory/factories/pipelines"
}